api_doc_mcp_server/__init__.py
api_doc_mcp_server/config.py
api_doc_mcp_server/main.py
api_doc_mcp_server/workflow.py
api_doc_mcp_server-1.0.7.dist-info/METADATA
api_doc_mcp_server-1.0.7.dist-info/WHEEL
api_doc_mcp_server-1.0.7.dist-info/entry_points.txt
api_doc_mcp_server-1.0.7.dist-info/top_level.txt
api_doc_mcp_server-1.0.7.dist-info/RECORD
