Metadata-Version: 2.4
Name: api-doc-mcp-server
Version: 1.0.7
Summary: An MCP tool for automatically generating API documentation that can be integrated with Cursor
Home-page: https://github.com/your-username/api-doc-mcp-server
Author: Your Name
Author-email: your.email@example.com
Classifier: Development Status :: 4 - Beta
Classifier: Intended Audience :: Developers
Classifier: License :: OSI Approved :: MIT License
Classifier: Operating System :: OS Independent
Classifier: Programming Language :: Python :: 3
Classifier: Programming Language :: Python :: 3.8
Classifier: Programming Language :: Python :: 3.9
Classifier: Programming Language :: Python :: 3.10
Classifier: Programming Language :: Python :: 3.11
Requires-Python: >=3.8
Requires-Dist: mcp-server==0.1.4
Requires-Dist: fastapi>=0.68.0
Requires-Dist: uvicorn>=0.15.0
Dynamic: author
Dynamic: author-email
Dynamic: classifier
Dynamic: description
Dynamic: description-content-type
Dynamic: home-page
Dynamic: requires-dist
Dynamic: requires-python
Dynamic: summary
